kfwy/H2O2.py
kfwy/NADHRedox.py
kfwy/__init__.py
kfwy/membrane_potential.py
kfwy/merge_h2o2.py
kfwy/merge_mp.py
kfwy/merge_nadh.py
kfwy-0.0.17.dist-info/LICENSE
kfwy-0.0.17.dist-info/METADATA
kfwy-0.0.17.dist-info/WHEEL
kfwy-0.0.17.dist-info/top_level.txt
kfwy-0.0.17.dist-info/RECORD
