Metadata-Version: 2.1
Name: kfwy
Version: 0.0.17
Summary: A data analysis toolkit for the KFW lab (Windows)
Home-page: https://github.com/tiffkwin/KFW
Author: Tiffany Nguyen
License: UNKNOWN
Platform: UNKNOWN
Classifier: Programming Language :: Python :: 2.7
Classifier: License :: OSI Approved :: Apache Software License
Classifier: Operating System :: Microsoft :: Windows
